<ArrayOfPerformance xmlns:i="http://www.w3.org/2001/XMLSchema-instance" xmlns="http://schemas.datacontract.org/2004/07/DTO"><Performance><Mark>69</Mark><Rank>1</Rank><School>Middeniya Central</School><StudentName>S.Tharuka Liyanage (G)</StudentName></Performance><Performance><Mark>66</Mark><Rank>2</Rank><School>Katuwana National C. </School><StudentName>W.Bhashitha Mihiranga (B)</StudentName></Performance><Performance><Mark>66</Mark><Rank>2</Rank><School>Katuwana National C. </School><StudentName>W.Bhashitha Mihiranga (B)</StudentName></Performance><Performance><Mark>47</Mark><Rank>4</Rank><School>Theraputtha N.C.</School><StudentName>V. P. Pasandi Ramalka (G)</StudentName></Performance><Performance><Mark>14</Mark><Rank>5</Rank><School>Modarawana M.V.</School><StudentName>P.M.Achintha Lakshan (B)</StudentName></Performance><Performance><Mark>12</Mark><Rank>6</Rank><School>Weeraketiya Central College</School><StudentName>Veenuka Sandeep (B)</StudentName></Performance></ArrayOfPerformance>